citybrain_official/__init__.py
citybrain_official/client.py
citybrain_official-0.15.dist-info/LICENSE
citybrain_official-0.15.dist-info/METADATA
citybrain_official-0.15.dist-info/WHEEL
citybrain_official-0.15.dist-info/top_level.txt
citybrain_official-0.15.dist-info/RECORD
