Metadata-Version: 2.1
Name: citybrain-official
Version: 0.15
Summary: retrieve data from citybrain.org
Home-page: UNKNOWN
Author: citybrain.org
Author-email: opensource@citybrain.org
License: UNKNOWN
Platform: UNKNOWN
Classifier: Programming Language :: Python :: 3
Classifier: License :: OSI Approved :: MIT License
Classifier: Operating System :: OS Independent
Requires-Python: >=3
License-File: LICENSE
Requires-Dist: requests
Requires-Dist: pandas
